maap_edsc_jupyter_extension/__init__.py
maap_edsc_jupyter_extension/_version.py
maap_edsc_jupyter_extension-1.1.2.data/data/share/jupyter/labextensions/maap_edsc_jupyter_extension/package.json
maap_edsc_jupyter_extension-1.1.2.data/data/share/jupyter/labextensions/maap_edsc_jupyter_extension/static/277.4f9d282c1e4246c2d64c.js
maap_edsc_jupyter_extension-1.1.2.data/data/share/jupyter/labextensions/maap_edsc_jupyter_extension/static/277.4f9d282c1e4246c2d64c.js.LICENSE.txt
maap_edsc_jupyter_extension-1.1.2.data/data/share/jupyter/labextensions/maap_edsc_jupyter_extension/static/373.a66bf2d53a8be9703647.js
maap_edsc_jupyter_extension-1.1.2.data/data/share/jupyter/labextensions/maap_edsc_jupyter_extension/static/48.c76406f95aa7fe325cf7.js
maap_edsc_jupyter_extension-1.1.2.data/data/share/jupyter/labextensions/maap_edsc_jupyter_extension/static/634.56834f954295b1762d44.js
maap_edsc_jupyter_extension-1.1.2.data/data/share/jupyter/labextensions/maap_edsc_jupyter_extension/static/692.a551eb9ef550ca44dffb.js
maap_edsc_jupyter_extension-1.1.2.data/data/share/jupyter/labextensions/maap_edsc_jupyter_extension/static/692.a551eb9ef550ca44dffb.js.LICENSE.txt
maap_edsc_jupyter_extension-1.1.2.data/data/share/jupyter/labextensions/maap_edsc_jupyter_extension/static/728.68627e761beaa4d3beb1.js
maap_edsc_jupyter_extension-1.1.2.data/data/share/jupyter/labextensions/maap_edsc_jupyter_extension/static/remoteEntry.efdd4aa84b479ec0fd09.js
maap_edsc_jupyter_extension-1.1.2.data/data/share/jupyter/labextensions/maap_edsc_jupyter_extension/static/style.js
maap_edsc_jupyter_extension-1.1.2.data/data/share/jupyter/labextensions/maap_edsc_jupyter_extension/static/third-party-licenses.json
maap_edsc_jupyter_extension-1.1.2.data/data/share/jupyter/labextensions/maap_edsc_jupyter_extension/install.json
maap_edsc_jupyter_extension-1.1.2.dist-info/METADATA
maap_edsc_jupyter_extension-1.1.2.dist-info/WHEEL
maap_edsc_jupyter_extension-1.1.2.dist-info/licenses/LICENSE
maap_edsc_jupyter_extension-1.1.2.dist-info/RECORD
